dash_material_ui/Accordion.py
dash_material_ui/Alert.py
dash_material_ui/App.py
dash_material_ui/AppBar.py
dash_material_ui/AutoLayout.py
dash_material_ui/Backdrop.py
dash_material_ui/Button.py
dash_material_ui/ButtonGroup.py
dash_material_ui/Calculator.py
dash_material_ui/Card.py
dash_material_ui/CheckBoxTable.py
dash_material_ui/CustomSpeedDial.py
dash_material_ui/DashMaterialUI.py
dash_material_ui/Form.py
dash_material_ui/Grid.py
dash_material_ui/Item.py
dash_material_ui/Menu.py
dash_material_ui/Pagination.py
dash_material_ui/Paper.py
dash_material_ui/Popover.py
dash_material_ui/RadioGroup.py
dash_material_ui/SecondComponent.py
dash_material_ui/Select.py
dash_material_ui/Slider.py
dash_material_ui/Switch.py
dash_material_ui/Table.py
dash_material_ui/__init__.py
dash_material_ui/_imports_.py
dash_material_ui/dash_material_ui.min.js
dash_material_ui/dash_material_ui.min.js.map
dash_material_ui/metadata.json
dash_material_ui/package-info.json
dash_mui_ploomber-0.0.4.dist-info/LICENSE
dash_mui_ploomber-0.0.4.dist-info/METADATA
dash_mui_ploomber-0.0.4.dist-info/WHEEL
dash_mui_ploomber-0.0.4.dist-info/top_level.txt
dash_mui_ploomber-0.0.4.dist-info/RECORD
