Metadata-Version: 2.1
Name: dash-mui-ploomber
Version: 0.0.4
Summary: Material UI for Dash
Author: Ploomber Inc <contact@ploomber.io>
License: Apache-2.0
Classifier: Framework :: Dash
License-File: LICENSE
